LICENSE
README.md
nautobot_meme_otd/__init__.py
nautobot_meme_otd/navigation.py
nautobot_meme_otd/templates/nautobot_meme_otd/meme-otd.html
nautobot_meme_otd/tests/__init__.py
nautobot_meme_otd/tests/test_api.py
nautobot_meme_otd/tests/test_basic.py
nautobot_meme_otd/urls.py
nautobot_meme_otd/views.py
nautobot_plugin_meme_otd-1.0.0.dist-info/LICENSE
nautobot_plugin_meme_otd-1.0.0.dist-info/WHEEL
nautobot_plugin_meme_otd-1.0.0.dist-info/METADATA
nautobot_plugin_meme_otd-1.0.0.dist-info/RECORD
