Metadata-Version: 2.1
Name: nautobot-plugin-meme-otd
Version: 1.0.0
Summary: Nautobot Meme Of The Day Plugin
Home-page: https://github.com/whitej6/nautobot-plugin-meme-otd
License: Apache-2.0
Keywords: nautobot,nautobot-plugin
Author: Jeremy White
Author-email: jeremy.white@networktocode.com
Requires-Python: >=3.7,<4.0
Classifier: License :: OSI Approved :: Apache Software License
Classifier: Programming Language :: Python :: 3
Classifier: Programming Language :: Python :: 3.7
Classifier: Programming Language :: Python :: 3.8
Classifier: Programming Language :: Python :: 3.9
Classifier: Programming Language :: Python :: 3.10
Classifier: Programming Language :: Python :: 3.11
Provides-Extra: nautobot
Requires-Dist: importlib-metadata (==4.13.0)
Requires-Dist: nautobot (>=1.4.0,<2.0.0); extra == "nautobot"
Project-URL: Repository, https://github.com/whitej6/nautobot-plugin-meme-otd
